foostitch/__init__.py
foostitch/__main__.py
lib/foostitch/__init__.py
lib/foostitch/__main__.py
foostitch-1.1.0.dist-info/LICENSE
foostitch-1.1.0.dist-info/METADATA
foostitch-1.1.0.dist-info/WHEEL
foostitch-1.1.0.dist-info/entry_points.txt
foostitch-1.1.0.dist-info/top_level.txt
foostitch-1.1.0.dist-info/RECORD
