Metadata-Version: 2.1
Name: foostitch
Version: 1.1.0
Summary: A utility for assembling cloud-init user-data from a repository of templates.
Home-page: https://github.com/ldgabbay/foostitch
Author: Lynn Gabbay
Author-email: gabbay@gmail.com
License: MIT
Classifier: Development Status :: 5 - Production/Stable
Classifier: Intended Audience :: Developers
Classifier: License :: OSI Approved :: MIT License
Classifier: Operating System :: OS Independent
Classifier: Programming Language :: Python :: 3
Classifier: Programming Language :: Python :: 3.6
Classifier: Programming Language :: Python :: 3.7
Classifier: Programming Language :: Python :: 3.8
Classifier: Programming Language :: Python :: 3.9
Classifier: Programming Language :: Python :: 3.10
Classifier: Programming Language :: Python :: 3.11
Classifier: Programming Language :: Python :: 3 :: Only
Classifier: Topic :: Software Development :: Libraries :: Python Modules
Requires-Python: >=3.6, <4
License-File: LICENSE
Requires-Dist: foostache ~=1.3
Requires-Dist: mkciud ~=1.0
